README.txt
buildout.cfg
setup.cfg
setup.py
test-plone-3.3.x.cfg
test-plone-4.0.x.cfg
Products/__init__.py
Products.ProtectedFile.egg-info/PKG-INFO
Products.ProtectedFile.egg-info/SOURCES.txt
Products.ProtectedFile.egg-info/dependency_links.txt
Products.ProtectedFile.egg-info/entry_points.txt
Products.ProtectedFile.egg-info/namespace_packages.txt
Products.ProtectedFile.egg-info/not-zip-safe
Products.ProtectedFile.egg-info/requires.txt
Products.ProtectedFile.egg-info/top_level.txt
Products/ProtectedFile/DEPENDS.txt
Products/ProtectedFile/LICENSE.GPL
Products/ProtectedFile/LICENSE.txt
Products/ProtectedFile/Permissions.py
Products/ProtectedFile/README.txt
Products/ProtectedFile/TODO.txt
Products/ProtectedFile/__init__.py
Products/ProtectedFile/config.py
Products/ProtectedFile/configure.zcml
Products/ProtectedFile/utils.py
Products/ProtectedFile/version.txt
Products/ProtectedFile/Extensions/Install.py
Products/ProtectedFile/Extensions/__init__.py
Products/ProtectedFile/i18n/ProtectedFile.pot
Products/ProtectedFile/skins/ProtectedFile/mail_file_address_template.dtml
Products/ProtectedFile/skins/ProtectedFile/protectedfile_confirm_mail.cpy
Products/ProtectedFile/skins/ProtectedFile/protectedfile_confirm_mail.cpy.metadata
Products/ProtectedFile/skins/ProtectedFile/protectedfile_email_list.pt
Products/ProtectedFile/skins/ProtectedFile/protectedfile_email_list.pt.metadata
Products/ProtectedFile/skins/ProtectedFile/protectedfile_emailed.pt
Products/ProtectedFile/skins/ProtectedFile/protectedfile_view.cpt
Products/ProtectedFile/skins/ProtectedFile/protectedfile_view.cpt.metadata
Products/ProtectedFile/skins/ProtectedFile/validate_email_protectedfile.vpy
Products/ProtectedFile/tests/ProtectedFileTestCase.py
Products/ProtectedFile/tests/__init__.py
Products/ProtectedFile/tests/framework.py
Products/ProtectedFile/tests/runalltests.py
Products/ProtectedFile/tests/testKeyManager.py
Products/ProtectedFile/tests/testProtectedFile.py
Products/ProtectedFile/tests/testSkeleton.py
Products/ProtectedFile/types/ProtectedFile.py
Products/ProtectedFile/types/__init__.py
docs/HISTORY.txt
docs/INSTALL.txt
docs/LICENSE.GPL
docs/LICENSE.txt