Metadata-Version: 1.0
Name: Products.ProtectedFile
Version: 0.1.1
Summary: 'Anonymous users must provide a valid email to download the file.'
Home-page: http://plone.org/products/protected-file
Author: Jarn & Simula Research Laboratory
Author-email: info@jarn.com
License: GPL
Keywords: file
Platform: UNKNOWN
Classifier: Framework :: Plone
Classifier: Programming Language :: Python
Classifier: Topic :: Software Development :: Libraries :: Python Modules
